krazy/__init__.py
krazy/data_science.py
krazy/frontend_tkinter_ready.py
krazy/gsheet_initialize.py
krazy/postgres_utilities.py
krazy/reconciler.py
krazy/sql_utilities.py
krazy/sqlite_utilities.py
krazy/utility_functions.py
krazy/ai/__init__.py
krazy/ai/agent.py
krazy/ai/api_server.py
krazy/ai/general.py
krazy/ai/rag.py
krazy/ai/tools.py
krazy-0.23.6.dist-info/licenses/LICENSE
krazy-0.23.6.dist-info/METADATA
krazy-0.23.6.dist-info/WHEEL
krazy-0.23.6.dist-info/top_level.txt
krazy-0.23.6.dist-info/RECORD
